{
  "site": "Modern Meadmaking Wiki",
  "source": "https://wiki.meadtools.com/",
  "crawl_scope": "Main page + all first-level linked pages within wiki.meadtools.com",
  "generated": "2026-07-20",
  "pages": [
    {
      "title": "Main Page",
      "url": "https://wiki.meadtools.com/en/home",
      "keywords": ["mead", "meadmaking", "wiki", "r/mead", "reddit", "getting started", "FAQ", "ingredients", "process", "resources", "recipes", "contribute", "discord"]
    },
    {
      "title": "Please Help",
      "url": "https://wiki.meadtools.com/en/please_help",
      "keywords": ["wiki contribution", "stub pages", "needs content", "guides", "competitions", "barrels", "filtration", "balancing", "editing guidelines"]
    },
    {
      "title": "Getting Started",
      "url": "https://wiki.meadtools.com/en/faq/getting_started",
      "keywords": ["beginner", "mead basics", "honey", "water", "yeast", "nutrients", "fruit", "melomel", "metheglin", "cyser", "rhodomel", "aeration", "staggered nutrient additions", "GotMead calculator", "recipes"]
    },
    {
      "title": "Glass Vs. Plastic",
      "url": "https://wiki.meadtools.com/en/faq/glass_vs_plastic",
      "keywords": ["carboy", "glass", "plastic", "PET carboy", "equipment", "fermentation vessel", "durability", "scratching", "weight"]
    },
    {
      "title": "Hydrometers",
      "url": "https://wiki.meadtools.com/en/faq/hydrometer",
      "keywords": ["hydrometer", "specific gravity", "Brix", "potential alcohol", "gravity reading", "final gravity", "original gravity", "meniscus", "stuck fermentation", "stabilization"]
    },
    {
      "title": "Honey (FAQ)",
      "url": "https://wiki.meadtools.com/en/faq/honey",
      "keywords": ["honey", "varietals", "monofloral", "wildflower honey", "honey locator", "raw honey", "orange blossom", "honey cost", "honey sourcing"]
    },
    {
      "title": "Yeast Selection",
      "url": "https://wiki.meadtools.com/en/faq/yeast_selection",
      "keywords": ["yeast", "71B-1122", "EC-1118", "Pasteur Blanc", "alcohol tolerance", "temperature range", "where to buy yeast"]
    },
    {
      "title": "LD Carlson Additives",
      "url": "https://wiki.meadtools.com/en/faq/ld_carlson_additives",
      "keywords": ["L.D. Carlson", "energizer", "nutrient", "DAP", "YAN", "PPM", "yeast nutrient dosing"]
    },
    {
      "title": "Alternative Nutrient Sources",
      "url": "https://wiki.meadtools.com/en/faq/alternative_nutrient_sources",
      "keywords": ["yeast nutrients", "dead yeast", "yeast hulls", "fruit nitrogen", "organic additives", "Fermaid O", "raisins", "YAN"]
    },
    {
      "title": "Basic Problems",
      "url": "https://wiki.meadtools.com/en/faq/basic_problems",
      "keywords": ["troubleshooting", "stuck fermentation", "slow fermentation", "honey separated", "cloudy mead", "off smells", "rotten egg smell", "hydrogen sulfide", "mistakes"]
    },
    {
      "title": "Overflow",
      "url": "https://wiki.meadtools.com/en/faq/overflow",
      "keywords": ["overflow", "foam-over", "fermenter size", "blowoff tube", "airlock", "krausen"]
    },
    {
      "title": "Stuck Fermentation",
      "url": "https://wiki.meadtools.com/en/protocol/stuck_fermentation",
      "keywords": ["stuck fermentation", "sluggish fermentation", "restart fermentation", "nutrition", "temperature", "pH", "fatty acids", "yeast hulls", "restart yeast", "fermentation never started"]
    },
    {
      "title": "Infection",
      "url": "https://wiki.meadtools.com/en/faq/infection",
      "keywords": ["infection", "mold", "pellicle", "lambic", "brettanomyces", "contamination", "sanitation", "spoilage"]
    },
    {
      "title": "Headspace",
      "url": "https://wiki.meadtools.com/en/faq/headspace",
      "keywords": ["headspace", "oxidation", "inert gas", "CO2", "topping up", "marbles", "aging vessel"]
    },
    {
      "title": "Stabilization and Backsweetening (FAQ)",
      "url": "https://wiki.meadtools.com/en/faq/stabilization_and_backsweetening",
      "keywords": ["stabilization", "back sweetening", "potassium metabisulfite", "potassium sorbate", "sterile filtration", "bottle pasteurization", "alcohol tolerance"]
    },
    {
      "title": "Illegal Ingredients",
      "url": "https://wiki.meadtools.com/en/faq/illegal_ingredients",
      "keywords": ["controlled substances", "homebrewing law", "legal ingredients", "regulation", "safety"]
    },
    {
      "title": "Chemicals",
      "url": "https://wiki.meadtools.com/en/faq/chemicals",
      "keywords": ["chemicals", "additives", "DAP", "Fermaid O", "sulfites", "sorbate", "organic vs inorganic", "food safety"]
    },
    {
      "title": "Honey (Ingredients)",
      "url": "https://wiki.meadtools.com/en/ingredients/honey",
      "keywords": ["honey", "wildflower honey", "monofloral honey", "raw honey", "honey processing", "honey sourcing", "honey vendors", "TrueSource", "honey quality"]
    },
    {
      "title": "Yeast (Ingredients)",
      "url": "https://wiki.meadtools.com/en/ingredients/yeast",
      "keywords": ["yeast strains", "wine yeast", "mead yeast", "beer yeast", "bread yeast", "kveik", "killer yeast", "temperature control", "pitch rate", "distiller's yeast", "wild yeast", "flocculation"]
    },
    {
      "title": "Water",
      "url": "https://wiki.meadtools.com/en/ingredients/water",
      "keywords": ["water", "distilled water", "spring water", "tap water", "chlorine", "chloramine", "well water", "Consumer Confidence Report", "campden tablets"]
    },
    {
      "title": "Nutrients (Ingredients)",
      "url": "https://wiki.meadtools.com/en/ingredients/nutrients",
      "keywords": ["yeast nutrients", "DAP", "Fermaid K", "Fermaid O", "GoFerm", "yeast energizer", "boiled bread yeast", "BBY", "YAN", "nitrogen sources"]
    },
    {
      "title": "Fruit (Ingredients)",
      "url": "https://wiki.meadtools.com/en/ingredients/fruit",
      "keywords": ["fruit", "melomel", "cyser", "apple mead", "whole fruit", "fruit sourcing", "freezing fruit", "primary vs secondary fruit addition"]
    },
    {
      "title": "Herbs and Spices",
      "url": "https://wiki.meadtools.com/en/ingredients/herbs_and_spices",
      "keywords": ["herbs", "spices", "metheglin", "cinnamon", "vanilla", "ginger", "citrus zest", "star anise", "cardamom", "tea infusion", "tincture"]
    },
    {
      "title": "Process Summary",
      "url": "https://wiki.meadtools.com/en/process/process_summary",
      "keywords": ["process overview", "ABV", "OG", "FG", "YAN", "SNA", "Meadcalc", "BatchBuildr", "brew day", "nutrition schedule", "step feeding", "acid tannin balance", "stabilization"]
    },
    {
      "title": "General Safety",
      "url": "https://wiki.meadtools.com/en/process/general_safety",
      "keywords": ["safety", "glass carboy handling", "plastic equipment", "stainless steel", "passivation", "pressure fermentation", "vacuum equipment", "bottle bombs", "botulism", "mold", "dry ice carbonation"]
    },
    {
      "title": "Cleaning",
      "url": "https://wiki.meadtools.com/en/process/cleaning",
      "keywords": ["cleaning", "sanitizing", "sterilizing", "PBW", "One-Step", "cleansers", "brushes", "hot water rinse"]
    },
    {
      "title": "Sanitation",
      "url": "https://wiki.meadtools.com/en/process/sanitation",
      "keywords": ["sanitation", "Star San", "iodine sanitizer", "potassium metabisulfite", "heat sanitizing", "no-rinse sanitizer", "equipment sanitation"]
    },
    {
      "title": "Yeast Rehydration",
      "url": "https://wiki.meadtools.com/en/process/rehydration",
      "keywords": ["rehydration", "GoFerm", "attemperation", "pitching yeast", "rehydration temperature", "dry yeast"]
    },
    {
      "title": "pH Adjustment",
      "url": "https://wiki.meadtools.com/en/process/ph_adjustment",
      "keywords": ["pH", "acid", "base", "potassium carbonate", "potassium bicarbonate", "calcium carbonate", "botulism", "pH testing"]
    },
    {
      "title": "Fermentation",
      "url": "https://wiki.meadtools.com/en/process/fermentation",
      "keywords": ["fermentation", "yeast", "original gravity", "oxygen", "nutrients", "temperature", "pH", "lag phase", "growth phase", "fermentation phases", "aging"]
    },
    {
      "title": "Aeration & Degassing",
      "url": "https://wiki.meadtools.com/en/process/aeration_degassing",
      "keywords": ["aeration", "degassing", "oxygen", "CO2", "stirring", "drill mix-stir", "vacuum degasser", "cap management", "fruit cap"]
    },
    {
      "title": "Staggered Nutrient Additions",
      "url": "https://wiki.meadtools.com/en/process/staggered_nutrient_additions",
      "keywords": ["SNA", "staggered nutrient additions", "nutrient schedule", "DAP", "Fermaid O", "fusel alcohols", "fermentation temperature spike"]
    },
    {
      "title": "Nutrient Schedules",
      "url": "https://wiki.meadtools.com/en/process/nutrient_schedules",
      "keywords": ["nutrient schedules", "TOSNA", "Balathustrius schedule", "Bray Denard", "Fermaid O", "Fermaid K", "DAP", "GoFerm", "potassium carbonate"]
    },
    {
      "title": "Step Feeding",
      "url": "https://wiki.meadtools.com/en/process/step_feeding",
      "keywords": ["step feeding", "honey additions", "gravity", "alcohol tolerance", "sweet mead", "ABV boost"]
    },
    {
      "title": "Stabilization",
      "url": "https://wiki.meadtools.com/en/process/stabilization",
      "keywords": ["stabilization", "potassium metabisulfite", "potassium sorbate", "campden tablets", "sulfite dosing", "sterile filtration", "pasteurization", "alcohol tolerance", "Delle stability", "bottle bombs"]
    },
    {
      "title": "Bench Trials",
      "url": "https://wiki.meadtools.com/en/process/bench_trials",
      "keywords": ["bench trials", "stock solutions", "dosing", "PPM", "tannin", "acid", "fining agent testing", "taste trial"]
    },
    {
      "title": "Back Sweetening",
      "url": "https://wiki.meadtools.com/en/process/back_sweeten",
      "keywords": ["back sweetening", "honey addition", "specific gravity", "non-fermentable sugar", "xylitol", "lactose", "sweetness balance"]
    },
    {
      "title": "Fining Agents",
      "url": "https://wiki.meadtools.com/en/process/fining",
      "keywords": ["fining agents", "clarity", "bentonite", "gelatin", "isinglass", "chitosan", "kieselsol", "sparkalloid", "pectic enzyme", "pectin haze", "cold crashing", "filtration"]
    },
    {
      "title": "Aging",
      "url": "https://wiki.meadtools.com/en/process/aging",
      "keywords": ["aging", "bulk aging", "bottle aging", "headspace", "oxidation", "corks", "sulfites", "oak", "clarity"]
    },
    {
      "title": "Packaging",
      "url": "https://wiki.meadtools.com/en/process/packaging",
      "keywords": ["bottling", "kegging", "corks", "crown caps", "EZ caps", "bottle choices", "bottling process", "kegs", "closures"]
    },
    {
      "title": "Equipment Overview",
      "url": "https://wiki.meadtools.com/en/resources/equipment",
      "keywords": ["equipment", "fermentation vessels", "carboys", "buckets", "airlocks", "hydrometers", "refractometers", "gram scale", "siphon", "bottling equipment", "kegging equipment"]
    },
    {
      "title": "Additive Weight to Volume Conversions",
      "url": "https://wiki.meadtools.com/en/resources/additive_weight_to_volume_conversions",
      "keywords": ["weight to volume", "honey conversion", "Fermaid O", "Fermaid K", "GoFerm", "DAP", "potassium sorbate", "measurements"]
    },
    {
      "title": "Advanced Nutrients in Mead Making",
      "url": "https://wiki.meadtools.com/en/resources/advanced_nutrients",
      "keywords": ["advanced nutrients", "YAN", "white paper", "nutrition"]
    },
    {
      "title": "Additional Reading",
      "url": "https://wiki.meadtools.com/en/resources/reading_list",
      "keywords": ["reading list", "books", "Compleat Meadmaker", "Scott Labs handbook", "BJCP guidelines", "wine chemistry", "resources"]
    },
    {
      "title": "Academic Journals",
      "url": "https://wiki.meadtools.com/en/resources/academic_journals",
      "keywords": ["academic journals", "research", "nitrogen uptake", "fusel alcohols", "Ehrlich pathway", "mead fermentation studies", "pectinase", "methanol"]
    },
    {
      "title": "Style Guidelines",
      "url": "https://wiki.meadtools.com/en/guides/style_guidelines",
      "keywords": ["BJCP", "mead styles", "traditional mead", "melomel", "cyser", "pyment", "braggot", "metheglin", "hydromel", "sack", "bochet", "acerglyn", "capsicumel"]
    },
    {
      "title": "Starter Recipes",
      "url": "https://wiki.meadtools.com/en/recipes",
      "keywords": ["recipes", "beginner recipes", "traditional mead recipe", "melomel recipe", "cyser recipe", "metheglin recipe", "braggot recipe", "bochet recipe"]
    },
    {
      "title": "User Recipes",
      "url": "https://wiki.meadtools.com/en/userrecipes",
      "keywords": ["user recipes", "crowdsourced recipes", "cyser", "bochet", "capsicumel", "metheglin", "braggot", "acerglyn", "melomel"]
    }
  ]
}
